monoscope_fastapi/__init__.py
monoscope_fastapi-1.0.0.dist-info/METADATA
monoscope_fastapi-1.0.0.dist-info/WHEEL
monoscope_fastapi-1.0.0.dist-info/top_level.txt
monoscope_fastapi-1.0.0.dist-info/RECORD
