Metadata-Version: 2.1
Name: monoscope-fastapi
Version: 1.0.0
Author: Monoscope
Author-email: hello@apitoolkit.io
Requires-Dist: fastapi
Requires-Dist: monoscope-common
Requires-Dist: opentelemetry-api>=1.0.0
